<!DOCTYPE frameset SYSTEM "frameset.dtd">
<frameset>
<note/>
<predicate lemma="arson">
<note/>
<roleset framnet="" id="arson.01" name="criminal fire-setting" source="" vncls="">
<roles>
<role descr="fire-setter" f="pag" n="0"/>
<note/>
<role descr="property burned" f="ppt" n="1"/>
</roles>
<note>Added by Julia based on BOLT.</note>
<example name="with PRD" src="BOLT" type="">
<inflection aspect="ns" form="ns" person="ns" tense="ns" voice="ns"/>
<text>As a result , basically natural disasters happened in the past , now the disasters that take place in Japan are man - made , which are the consequences of the accumulation of murders and arson aimed at destroying the world . Just like drawing fire to themselves .</text>
<note/>
<rel f="">arson</rel>
<arg f="prd" n="m">aimed at destroying the world</arg>
</example>
</roleset>
</predicate>
</frameset>
