<!DOCTYPE frameset SYSTEM "frameset.dtd">
<frameset>
  <predicate lemma="brown">
    <roleset id="brown.01" name="(cause to) be brown by cooking or tanning">
      <aliases>
        <alias framenet="Apply_heat" pos="v" verbnet="">brown</alias>
      </aliases>
      <note>BROWN-V NOTES: Based on internet usage examples, expansion via VN. Verbnet entry cooking-45.3. Frame created by Claire (from brown.01-v)</note>
      <roles>
        <role descr="causer of browning (eg sun, cook)" f="pag" n="0">
          <vnrole vncls="45.3" vntheta="agent"/>
        </role>
        <role descr="browned entity" f="ppt" n="1">
          <vnrole vncls="45.3" vntheta="patient"/>
        </role>
        <role descr="description of browning, attribute of arg1" f="prd" n="2">
          <vnrole vncls="45.3" vntheta="result"/>
        </role>
      </roles>
      <example name="Impersonal, cooking" src="" type="">
        <text>*PRO* brown the chicken on both sides until juices run clear.</text>
        <arg f="" n="0">*PRO*</arg>
        <rel f="">brown</rel>
        <arg f="" n="1">the chicken</arg>
        <arg f="loc" n="m">on both sides</arg>
        <arg f="tmp" n="m">until juices run clear</arg>
      </example>
      <example name="All arguments tanning" src="" type="">
        <text>The sun browned Mary a deep golden.</text>
        <arg f="" n="0">The sun</arg>
        <rel f="">browned</rel>
        <arg f="" n="1">mary</arg>
        <arg f="" n="2">a deep golden</arg>
      </example>
    </roleset>
  </predicate>
</frameset>
