<!DOCTYPE frameset SYSTEM "frameset.dtd">
<frameset>
  <predicate lemma="circumferential">
    <roleset id="circumferential.01" name="involving the circumference">
      <aliases>
        <alias framenet="" pos="j" verbnet="">circumferential</alias>
      </aliases>
      <note>CIRCUMFERENTIAL-J NOTES: Added automatically by Julia. Related to noncircumferential.01 (from circumferential.01-j)</note>
      <roles>
        <role descr="circumferential entity" f="ppt" n="1"/>
        <role descr="to what (interior)" f="ppt" n="2"/>
      </roles>
      <example name="" src="" type="">
        <text>The air outlet has a frame that is circumferential and sealed off from the housing</text>
      </example>
    </roleset>
  </predicate>
</frameset>
