<!DOCTYPE frameset SYSTEM "frameset.dtd">
<frameset>
  <predicate lemma="condemn">
    <roleset id="condemn.01" name="express strong disapproval of">
      <aliases>
        <alias framenet="Judgment_communication" pos="v" verbnet="">condemn</alias>
        <alias framenet="" pos="n" verbnet="">condemnation</alias>
      </aliases>
      <note>CONDEMN-V NOTES: Member of VNcls judgement-33, suspect-81. (from condemn.01-v)</note>
      <roles>
        <role descr="condemner" f="PAG" n="0">
          <vnrole vncls="33" vntheta="Agent"/>
          <vnrole vncls="81" vntheta="Agent"/>
        </role>
        <role descr="condemned" f="PPT" n="1">
          <vnrole vncls="33" vntheta="Theme"/>
          <vnrole vncls="81" vntheta="Theme"/>
        </role>
        <role descr="grounds for condemnation, condemned as" f="cau" n="2">
          <vnrole vncls="81" vntheta="Attribute"/>
        </role>
        <role descr="destination" f="gol" n="3"/>
      </roles>
      <example name="straight transitive" src="" type="">
        <inflection aspect="perfect" form="participle" person="ns" tense="past" voice="active"/>
        <text>The two, Szeto Wah and Martin Lee, were deemed unfit because they had condemned China's crackdown on its pro-democracy movement.</text>
        <arg f="" n="0">they</arg>
        <rel f="">condemned</rel>
        <arg f="" n="1">China's crackdown on its pro-democracy movement</arg>
      </example>
      <example name="condemn as" src="" type="">
        <inflection aspect="ns" form="full" person="ns" tense="past" voice="active"/>
        <text>A White House spokesman condemned the truce suspension as ``deplorable'' but brushed off talk of renewing military funding for the insurgents.</text>
        <arg f="" n="0">A White House spokesman</arg>
        <rel f="">condemned</rel>
        <arg f="" n="1">the truce suspension</arg>
        <arg f="" n="2">as deplorable</arg>
      </example>
      <example name="condemn to" src="" type="">
        <inflection aspect="ns" form="infinitive" person="ns" tense="ns" voice="ns"/>
        <text>For instance, juries-1 would have *trace*-1 to consider specific ``aggravating'' and ``mitigating'' factors before *trace*-1 deciding whether *trace*-1 to condemn someone to death.</text>
        <arg f="" n="0">*trace*</arg>
        <rel f="">condemn</rel>
        <arg f="" n="1">someone</arg>
        <arg f="" n="3">to death</arg>
      </example>
      <example name="with grounds as gerund" src="criticize.01" type="">
        <text>The internal investigation also condemned MiniScribe's auditors, Coopers&amp; Lybrand, for allegedly ignoring numerous red flags.</text>
        <arg f="" n="0">The internal investigation</arg>
        <arg f="dis" n="m">also</arg>
        <rel f="">condemned</rel>
        <arg f="" n="1">MiniScribe's auditors, Coopers&amp; Lybrand,</arg>
        <arg f="" n="2">for allegedly ignoring numerous red flags</arg>
      </example>
      <example name="with grounds as full clause" src="criticize.01" type="">
        <text>A Poquet spokesman, for example, condemns the Atari Portfolio because it requires three batteries while the Poquet needs only two.</text>
        <arg f="" n="0">A Poquet spokesman</arg>
        <arg f="dis" n="m">for example</arg>
        <rel f="">condemns</rel>
        <arg f="" n="1">the Atari Portfolio</arg>
        <arg f="" n="2">because it requires three batteries while the Poquet needs only two</arg>
      </example>
      <example name="args 2 and 3 together" src="" type="">
        <inflection aspect="ns" form="full" person="ns" tense="past" voice="active"/>
        <text>Mary condemned John to prison for his habit of waking her with icy-cold water.</text>
        <arg f="" n="0">Mary</arg>
        <rel f="">condemned</rel>
        <arg f="" n="1">John</arg>
        <arg f="" n="2">to prison</arg>
        <arg f="" n="3">for his habit of waking her with icy-cold water</arg>
      </example>
    </roleset>
  </predicate>
</frameset>
