<!DOCTYPE frameset SYSTEM "frameset.dtd">
<frameset>
	<predicate lemma="cooling">
		<roleset framnet="-" id="cooling.01" name="cause to be colder" source="verb-cool.01" vncls="45.4">
			<roles>
				<role descr="cause of cooling" f="pag" n="0">
<vnrole vncls="45.4" vntheta="agent"/>
</role>
				<role descr="thing getting colder" f="ppt" n="1">
<vnrole vncls="45.4" vntheta="patient"/>
</role>
			
<note/>
</roles>
			
		
<note>Roleset based on instances in BOLT P01.  Comparison to verb entry cool.01, which maps to VN class 45.4, no FN for gerund.</note>
<example name="Metaphorical, all args" src="" type="">
<inflection aspect="ns" form="ns" person="ns" tense="ns" voice="ns"/>
<text>his cooling of expectations</text>
<note/>
<arg f="" n="0">his</arg>
<rel f="">cooling</rel>
<arg f="" n="1">of expectations</arg>
</example>
</roleset>
	
<note/>
</predicate>

<note/>
</frameset>
