<!DOCTYPE frameset SYSTEM "frameset.dtd">
<frameset>
    <predicate lemma="describe">
        
        
        <roleset framnet="Communicate_categorization" id="describe.01" name="assign a label or attribute" vncls="29.2">
            <roles>
                <role descr="describer" f="" n="0">
                    
                    <vnrole vncls="29.2" vntheta="agent"/>
                </role>
                
                <role descr="thing described" f="" n="1">
                    
                    <vnrole vncls="29.2" vntheta="theme"/>
                </role>
                
                <role descr="secondary attribute, described-as" f="" n="2">
                    
                    <vnrole vncls="29.2" vntheta="predicate"/>
                </role>
                
                <note/>
            </roles>
            
            <example name="all args" src="" type="">
                <text>The SEC documents describe those chips, which are made of gallium
                    arsenide, as *trace* being so fragile and minute they will require
                    special robotic handling equipment.
                </text>
                <arg f="" n="0">The SEC documents</arg>
                <rel f="">describe</rel>
                <arg f="" n="1">those chips, which are made of gallium arsenide</arg>
                <arg f="" n="2">as *trace* being so fragile and minute they will   require special robotic handling equipment</arg>
                <note/>
            </example>
            
            <example name="inverted attribute" src="" type="">
                <text>a ``seething mass,'' as one trader described it.</text>
                <arg f="" n="2">a ``seething mass,''</arg>
                <arg f="" n="0">one trader</arg>
                <rel f="">described</rel>
                <arg f="" n="1">it</arg>
                <note>only tag arg2 if it is actually in the span or has a trace.</note>
            </example>
            
            <example name="no attribute" src="" type="">
                <text>It didn't describe the source of funds or the specific terms of
                    StatesWest securities which were part of the offer.
                </text>
                <arg f="" n="0">It</arg>
                <arg f="neg" n="m">n't</arg>
                <rel f="">describe</rel>
                <arg f="" n="1">the source of funds or the specific terms of StatesWest securities which were part of the offer</arg>
                <note/>
            </example>
            
            
            
            <note>Comparison to 'call' attributive sense. Member of VNcls characterize-29.2-1-1.</note>
        </roleset>
        <note>Frames file for 'describe' based on survey of sentences in financial
            subcorpus.
        </note>
    </predicate>
    <note/>
</frameset>
