<?xml version="1.0" encoding="utf-8" standalone="no"?>
<!DOCTYPE frameset PUBLIC "-//PB//PropBank Frame v3.4 Transitional//EN" "http://propbank.org/specification/dtds/v3.4/frameset.dtd">
<frameset>
  <predicate lemma="dwarf">
    <roleset id="dwarf.01" name="be dramatically larger than">
      <aliases>
        <alias pos="v">dwarf</alias>
      </aliases>
      <roles>
        <role descr="larger thing" f="PAG" n="0"/>
        <role descr="smaller thing" f="PPT" n="1"/>
      </roles>
      <usagenotes>
        <usage resource="PropBank" version="1.0" inuse="+"/>
        <usage resource="PropBank" version="2.1.5" inuse="+"/>
        <usage resource="PropBank" version="3.1" inuse="+"/>
        <usage resource="PropBank" version="3.4" inuse="+"/>
        <usage resource="AMR" version="2019" inuse="+"/>
        <usage resource="PropBank" version="Flickr 1.0" inuse="+"/>
        </usagenotes>
      <lexlinks/>
      <example name="passivized" src="">
        <text>Courtaulds ' restructuring is among the largest thus far in Britain , though it is dwarfed by B.A.T Industries PLC 's plans to spin off roughly # 4 billion in assets to help fend off a takeover bid from Anglo - French financier Sir James Goldsmith .</text>
        <propbank>
          <rel relloc="15">dwarfed</rel>
          <arg type="ARG1" start="13" end="13">it</arg>
          <arg type="ARG0" start="16" end="45">by B.A.T Industries PLC 's plans to spin off roughly # 4 billion in assets to help fend off a takeover bid from Anglo - French financier Sir James Goldsmith</arg>
        </propbank>
      </example>
      <note>DWARF-V NOTES: Frames file for 'dwarf' based on sentences in financial subcorpus. No Verbnet entry. No comparison. (from dwarf.01-v predicate notes)</note>
    </roleset>
  </predicate>
</frameset>