<?xml version="1.0" encoding="utf-8" standalone="no"?>
<!DOCTYPE frameset PUBLIC "-//PB//PropBank Frame v3.4 Transitional//EN" "http://propbank.org/specification/dtds/v3.4/frameset.dtd">
<frameset>
  <predicate lemma="flow">
    <roleset id="flow.01" name="move like water">
      <aliases>
        <alias pos="v">flow</alias>
        <alias pos="n">flow</alias>
      </aliases>
      <roles>
        <role descr="substance (ie, water)" f="PPT" n="1">
          <rolelinks>
            <rolelink class="entity_specific_modes_being-47.2" resource="VerbNet" version="verbnet3.3">theme</rolelink>
            <rolelink class="Fluidic_motion" resource="FrameNet" version="1.7">fluid</rolelink>
            <rolelink class="entity_specific_modes_being-47.2" resource="VerbNet" version="verbnet3.4">theme</rolelink>
          </rolelinks>
        </role>
        <role descr="direction" f="DIR" n="m">
          <rolelinks/>
        </role>
      </roles>
      <usagenotes>
        <usage resource="PropBank" version="1.0" inuse="+"/>
        <usage resource="PropBank" version="2.1.5" inuse="+"/>
        <usage resource="PropBank" version="3.1" inuse="+"/>
        <usage resource="PropBank" version="3.4" inuse="+"/>
        <usage resource="AMR" version="2019" inuse="+"/>
        <usage resource="PropBank" version="Flickr 1.0" inuse="+"/>
        </usagenotes>
      <lexlinks>
        <lexlink class="Fluidic_motion" confidence="0.8" resource="FrameNet" src="manual+strict-conv" version="1.7"/>
        <lexlink class="entity_specific_modes_being-47.2" confidence="0.8" resource="VerbNet" src="manual+strict-conv" version="verbnet3.3"/>
        <lexlink class="entity_specific_modes_being-47.2" confidence="1.0" resource="VerbNet" src="manualchecks" version="verbnet3.4"/>
      </lexlinks>
      <example name="flow-v: flow out of" src="">
        <text>Last week alone , an eye - popping $ 1.6 billion flowed out of the junk funds , or nearly 5 % of their total assets , according to estimates by Dalbar Financial Services Inc. , a Boston research firm .</text>
        <propbank>
          <rel relloc="11">flowed</rel>
          <arg type="ARGM-TMP" start="0" end="2">Last week alone</arg>
          <arg type="ARG1" start="4" end="10">an eye - popping $ 1.6 billion</arg>
          <arg type="ARGM-DIR" start="12" end="16">out of the junk funds</arg>
          <arg type="ARGM-ADV" start="27" end="39">according to estimates by Dalbar Financial Services Inc. , a Boston research firm</arg>
          <arg type="C-ARG1" start="18" end="25">or nearly 5 % of their total assets</arg>
        </propbank>
      </example>
      <example name="flow-v: flow through" src="">
        <text>The 4.9 million - share volume flowing through the Jacobson specialist operation was about five times normal for the stock .</text>
        <propbank>
          <rel relloc="6">flowing</rel>
          <arg type="ARG1" start="0" end="5">The 4.9 million - share volume</arg>
          <arg type="ARGM-DIR" start="7" end="11">through the Jacobson specialist operation</arg>
        </propbank>
      </example>
      <example name="flow-n: use goal for destination/end point" src="">
        <text>the flow of foreign capital to the U.S.</text>
        <propbank>
          <rel relloc="1">flow</rel>
          <arg type="ARG1" start="2" end="4">of foreign capital</arg>
          <arg type="ARGM-GOL" start="5" end="7">to the U.S.</arg>
        </propbank>
      </example>
      <example name="flow-n: use dir for source" src="">
        <text>cash flow from profits</text>
        <propbank>
          <rel relloc="1">flow</rel>
          <arg type="ARG1" start="0" end="0">cash</arg>
          <arg type="ARGM-DIR" start="2" end="3">from profits</arg>
        </propbank>
      </example>
      <example name="flow-n: arg 1" src="">
        <text>Talent flow</text>
        <propbank>
          <rel relloc="1">flow</rel>
          <arg type="ARG1" start="0" end="0">Talent</arg>
        </propbank>
      </example>
      <example name="flow-n: another nominal with an end point" src="">
        <text>The flow of water into the Shihmen Reservior</text>
        <propbank>
          <rel relloc="1">flow</rel>
          <arg type="ARG1" start="2" end="3">of water</arg>
          <arg type="ARGM-GOL" start="4" end="7">into the Shihmen Reservior</arg>
        </propbank>
      </example>
      <example name="flow-n: with purpose" src="">
        <text>The flow of infomation into a manufacture 's main computer network for use in business planning marketing and other operations</text>
        <propbank>
          <rel relloc="1">flow</rel>
          <arg type="ARG1" start="2" end="3">of infomation</arg>
          <arg type="ARGM-GOL" start="4" end="10">into a manufacture 's main computer network</arg>
          <arg type="ARGM-PRP" start="11" end="19">for use in business planning marketing and other operations</arg>
        </propbank>
      </example>
      <note>FLOW-V NOTES: Levin/Verbnet predicts an agentive reading, meaning "cause to flow",but we'll wait until we see an example. (from flow.01-v)</note>
      <note>FLOW-N NOTES: Based on nouns-00080. VN class entity_specific_modes_being-47.2. Updated by Julia. (from flow.01-n)</note>
    </roleset>
    <roleset id="flow.02" name="natural disaster: debris flow, pyroclastic flow">
      <aliases>
        <alias pos="n">flow</alias>
      </aliases>
      <roles>
        <role descr="substance, 'pyroclastic' or 'debris'. If 'mud', use 'mudflow' roleset" f="PPT" n="1"/>
        <role descr="volume, weight" f="EXT" n="2"/>
        <role descr="casualties/injuries" f="VSP" n="3"/>
        <role descr="damages/cost" f="VSP" n="4"/>
      </roles>
      <usagenotes>
        <usage resource="PropBank" version="1.0" inuse="-"/>
        <usage resource="PropBank" version="2.1.5" inuse="-"/>
        <usage resource="PropBank" version="3.1" inuse="+"/>
        <usage resource="PropBank" version="3.4" inuse="+"/>
        <usage resource="AMR" version="2019" inuse="-"/>
        <usage resource="PropBank" version="Flickr 1.0" inuse="+"/>
        </usagenotes>
      <lexlinks/>
      <example name="flow-n" src="">
        <text>I watched a Discovery Channel doc on Mt St Helens &amp; the 300 mph pyroclastic flow .</text>
        <propbank>
          <rel relloc="15">flow</rel>
          <arg type="ARGM-ADJ" start="12" end="13">300 mph</arg>
          <arg type="ARG1" start="14" end="14">pyroclastic</arg>
        </propbank>
      </example>
      <example name="flow-n" src="">
        <text>... and the 60,000 tonne debris flow at Montrose in theDandenong Ranges of Victoria in 1891 ( Moonand others 1992 ) .</text>
        <propbank>
          <rel relloc="6">flow</rel>
          <arg type="ARG2" start="3" end="4">60,000 tonne</arg>
          <arg type="ARG1" start="5" end="5">debris</arg>
        </propbank>
      </example>
      <note>FLOW-N NOTES: Added by Julia in a Natural Disaster roleset endeavor. Comparison to mudflow, lahar. (from flow.02-n)</note>
      <note>The "VSP" function tags on 'death/injury toll' and 'damages/cost' correspond to the RED cause relation.</note>
    </roleset>
  </predicate>
</frameset>