<!DOCTYPE frameset SYSTEM "frameset.dtd">
<frameset>
  <predicate lemma="moot">
    <roleset id="moot.01" name="consider, think carefully">
      <aliases>
        <alias framenet="" pos="v" verbnet="">moot</alias>
      </aliases>
      <note>MOOT-V NOTES: frameset created by Jena (from moot.01-v)</note>
      <roles>
        <role descr="thinker" f="pag" n="0">
          <vnrole vncls="29.2" vntheta="agent"/>
        </role>
        <role descr="object, thing under consideration" f="ppt" n="1">
          <vnrole vncls="29.2" vntheta="theme"/>
        </role>
      </roles>
      <example name="passivized" src="" type="">
        <text>[A golf course]-1 is mooted *-1.</text>
        <rel f="">mooted</rel>
        <arg f="" n="1">*-1</arg>
      </example>
    </roleset>
    <roleset id="moot.02" name="irrelevant">
      <aliases>
        <alias framenet="" pos="j" verbnet="">moot</alias>
      </aliases>
      <note>MOOT-J NOTES: Added by Julia.</note>
      <roles>
        <role descr="irrelevant thing" f="ppt" n="1"/>
      </roles>
      <example name="moot-j" src="" type="">
        <text>if obama kept his promise , this would be moot .	</text>
        <arg f="adv" n="m">if obama kept his promise</arg>
        <arg f="" n="1">this</arg>
        <arg f="mod" n="m">would</arg>
        <rel f="">moot</rel>
      </example>
    </roleset>
  </predicate>
</frameset>
