<!DOCTYPE frameset SYSTEM "frameset.dtd">
<frameset>
	<predicate lemma="naming">
		<roleset framnet="" id="naming.01" name="Calling, Giving a name" vncls="29.3" source="verb-name.01">
			<roles>
				<role descr="Namer" f="PAG" n="0">
					<vnrole vncls="29.3" vntheta="Agent"/>
				</role>
				<role descr="Named" f="PPT" n="1">
					<vnrole vncls="29.3" vntheta="Theme"/>
				</role>
				<role descr="Name given to Arg1" f="PRD" n="2">
					<vnrole vncls="29.3" vntheta="Result"/>
				</role>
				<note/>
			</roles>
			<example name="Arg0,1,2" src="" type="">
				<inflection aspect="ns" form="ns" person="ns" tense="ns" voice="ns"/>
				<text>
					A last source says that it was because Aina found rest in the area, which occasioned his naming the area as 'Isin.'
				</text>
				<arg f="" n="0">
					his
				</arg>
				<rel f="">
					naming
				</rel>
				<arg f="" n="1">
					the area
				</arg>
				<arg f="" n="2">
					as 'Isin'
				</arg>
				<note/>
			</example>
			<note>
				name.01
			</note>
		</roleset>
		<note/>
	</predicate>
	<note/>
</frameset>
