<?xml version="1.0" ?>
<frameset>
   <predicate lemma="overshadow">
      <roleset id="overshadow.01" name="to dominate, make insignificant by comparison">
         <aliases>
            <alias pos="v">overshadow</alias>
         </aliases>
         <roles>
            <role descr="entity dominating" f="PAG" n="0">
               <rolelinks>
                  <rolelink class="remedy-45.7" resource="VerbNet" version="verbnet3.3">agent</rolelink>
                  <rolelink class="remedy-45.7" resource="VerbNet" version="verbnet3.4">agent</rolelink>
               </rolelinks>
            </role>
            <role descr="entity overshadowed" f="PPT" n="1">
               <rolelinks>
                  <rolelink class="remedy-45.7" resource="VerbNet" version="verbnet3.3">patient</rolelink>
                  <rolelink class="remedy-45.7" resource="VerbNet" version="verbnet3.4">patient</rolelink>
               </rolelinks>
            </role>
         </roles>
         <usagenotes>
            <usage resource="PropBank" version="3.4" inuse="+" />
            <usage resource="AMR" version="2019" inuse="+" />
         </usagenotes>
         <lexlinks>
            <lexlink class="overshadow-v.1" confidence="0.1" resource="onsense" src="annot-overlap" version="on5">7</lexlink>
            <lexlink class="remedy-45.7" confidence="1.0" resource="VerbNet" src="manualchecks" version="verbnet3.4"/>
         </lexlinks>
         <example name="passive" src="">
            <text>One was that , despite his 62 regular-season wins over the past three seasons in the Land Beyond the Late News , he has been overshadowed [*] by his more-muscular mates and missed out on prizes that []might have been his due .</text>
            <rel relloc="25">overshadowed</rel>
            <arg end="22" f="" n="1" start="22">he</arg>
            <arg end="30" f="" n="0" start="27">by his more-muscular mates</arg>
         </example>
         <example name="transitive" src="">
            <text>The Japanese assault on the luxury market is rapidly overshadowing such European makes as Audi and Saab , which [] at least have clear brand images .</text>
            <rel relloc="9">overshadowing</rel>
            <arg end="6" f="" n="0" start="0">The Japanese assault on the luxury market</arg>
            <arg end="8" f="MNR" n="M" start="8">rapidly</arg>
            <arg end="25" f="" n="1" start="11">European makes as Audi and Saab , which [] at least have clear brand images</arg>
         </example>
         <note>OVERSHADOW-V NOTES: Frames file for 'overshadow' based on survey of sentences in the WSJ corpus. (from overshadow.01-v predicate notes)</note>
      </roleset>
   </predicate>
</frameset>
