<!DOCTYPE frameset SYSTEM "frameset.dtd">
<frameset>
  <predicate lemma="profit">
    <roleset id="profit.01" name="make money from, wages">
      <aliases>
        <alias framenet="" pos="n" verbnet="">profit</alias>
        <alias framenet="" pos="l" verbnet="">make_profit</alias>
        <alias framenet="" pos="v" verbnet="">profit</alias>
      </aliases>
      <note>PROFIT-V NOTES: Frames file for 'profit' based on sentences in financial subcorpus. No verbnet entry. No comparison. (from profit.01-v)</note>
      <note>PROFIT-N NOTES: Roleset based on verb entry profit.01 and OntoNotes sense groupings profit.01, profit.02; no mappings to VN. Framed by Claire (from profit.01-n)</note>
      <roles>
        <note>Use ARGM-GOL for beneficiary of profit when present. (from profit.01-n)</note>
        <role descr="entity making money" f="pag" n="0"/>
        <role descr="source" f="ppt" n="1"/>
        <role descr="the profit itself, amount" f="ppt" n="2"/>
      </roles>
      <example name="profit-v: transitive, typical" src="" type="">
        <text>...protects against stocks being relentlessly beaten downward by those-1 seeking *trace*-1 to profit from lower prices.</text>
        <arg f="" n="0">*trace*</arg>
        <rel f="">profit</rel>
        <arg f="" n="1">from lower prices</arg>
      </example>
      <example name="profit-n: NP only" src="NP only" type="NP only">
        <text>group net profit of $ 2.5 billion on revenue of $ 125.1 billion</text>
        <arg f="" n="0">group</arg>
        <rel f="">profit</rel>
        <arg f="" n="2">of $ 2.5 billion</arg>
        <arg f="" n="1">on revenue of $ 125.1 billion</arg>
      </example>
      <example name="profit-n: With manner only" src="With manner only" type="With manner only">
        <text>These investors are looking for a quick profit.</text>
        <arg f="mnr" n="m">quick</arg>
        <rel f="">profit</rel>
      </example>
      <example name="profit-n: preposition for source argument" src="" type="">
        <inflection aspect="ns" form="ns" person="ns" tense="ns" voice="ns"/>
        <text>George only made a twenty dollar profit each year on his crafts.</text>
        <arg f="" n="2">twenty dollar</arg>
        <rel f="">profit</rel>
        <arg f="tmp" n="m">each year</arg>
        <arg f="" n="1">on his crafts</arg>
      </example>
      <example name="profit-n: Metaphorical profit, with source only" src="Metaphorical profit, with source only" type="Metaphorical profit, with source only">
        <inflection aspect="ns" form="ns" person="ns" tense="ns" voice="ns"/>
        <text>I hope there is some profit in your seeing this play.</text>
        <arg f="" n="2">some</arg>
        <rel f="">profit</rel>
        <arg f="" n="1">in your seeing this play</arg>
      </example>
      <example name="profit-n: Source with &quot;of&quot; preposition" src="Source with &quot;of&quot; preposition" type="Source with &quot;of&quot; preposition">
        <inflection aspect="ns" form="ns" person="ns" tense="ns" voice="ns"/>
        <text>What's the profit of visiting the doctor if you won't take his advice.</text>
        <rel f="">profit</rel>
        <arg f="" n="1">of visiting the doctor</arg>
      </example>
    </roleset>
  </predicate>
  <predicate lemma="profitable">
    <roleset id="profitable.02" name="producing a profit">
      <aliases>
        <alias framenet="" pos="j" verbnet="">profitable</alias>
      </aliases>
      <note>PROFITABLE-J NOTES: Automatically created by Julia for unification as an alias file. (from profitable.01-j)</note>
      <roles>
        <role descr="entity making money" f="pag" n="0"/>
        <role descr="source" f="ppt" n="1"/>
        <role descr="the profit itself, amount" f="ppt" n="2"/>
      </roles>
      <example name="profitable-j" src="" type="">
        <text>weed management is profitable for irrigated rice farmers in Sahelian West Africa.</text>
        <arg f="" n="1">weed management</arg>
        <rel f="">profitable</rel>
        <arg f="" n="0">for irrigated rice farmers in Sahelian West Africa</arg>
      </example>
    </roleset>
  </predicate>
</frameset>
