<?xml version="1.0" encoding="utf-8" standalone="no"?>
<!DOCTYPE frameset PUBLIC "-//PB//PropBank Frame v3.4 Transitional//EN" "http://propbank.org/specification/dtds/v3.4/frameset.dtd">
<frameset>
  <predicate lemma="report">
    <roleset id="report.01" name="report, tell, writing/work-of-art, relating info, formally">
      <aliases>
        <alias pos="v">report</alias>
        <alias pos="n">report</alias>
        <alias pos="n">reporting</alias>
        <argalias arg="0" pos="n">reporter</argalias>
      </aliases>
      <roles>
        <role descr="Reporter" f="PAG" n="0">
          <rolelinks>
            <rolelink class="say-37.7-1" resource="VerbNet" version="verbnet3.3">agent</rolelink>
            <rolelink class="consider-29.9-1" resource="VerbNet" version="verbnet3.3">agent</rolelink>
            <rolelink class="characterize-29.2-1-2" resource="VerbNet" version="verbnet3.3">agent</rolelink>
            <rolelink class="Statement" resource="FrameNet" version="1.7">speaker</rolelink>
            <rolelink class="characterize-29.2-1-2" resource="VerbNet" version="verbnet3.4">agent</rolelink>
            <rolelink class="Reporting" resource="FrameNet" version="1.7">informer</rolelink>
          </rolelinks>
        </role>
        <role descr="theme (what is reported)" f="PPT" n="1">
          <rolelinks>
            <rolelink class="say-37.7-1" resource="VerbNet" version="verbnet3.3">topic</rolelink>
            <rolelink class="consider-29.9-1" resource="VerbNet" version="verbnet3.3">attribute</rolelink>
            <rolelink class="characterize-29.2-1-2" resource="VerbNet" version="verbnet3.3">attribute</rolelink>
            <rolelink class="Statement" resource="FrameNet" version="1.7">message</rolelink>
            <rolelink class="characterize-29.2-1-2" resource="VerbNet" version="verbnet3.4">theme</rolelink>
            <rolelink class="Reporting" resource="FrameNet" version="1.7">behavior</rolelink>
            <rolelink class="Reporting" resource="FrameNet" version="1.7">wrongdoer</rolelink>
          </rolelinks>
        </role>
        <role descr="entity reported to" f="GOL" n="2">
          <rolelinks>
            <rolelink class="say-37.7-1" resource="VerbNet" version="verbnet3.3">recipient</rolelink>
            <rolelink class="Statement" resource="FrameNet" version="1.7">addressee</rolelink>
            <rolelink class="Reporting" resource="FrameNet" version="1.7">authorities</rolelink>
          </rolelinks>
        </role>
        <role descr="topic (what is reported about)" f="VSP" n="3">
          <rolelinks>
            <rolelink class="Statement" resource="FrameNet" version="1.7">topic</rolelink>
            <rolelink class="Reporting" resource="FrameNet" version="1.7">behavior</rolelink>
          </rolelinks>
        </role>
      </roles>
      <usagenotes>
        <usage resource="PropBank" version="1.0" inuse="+"/>
        <usage resource="PropBank" version="2.1.5" inuse="+"/>
        <usage resource="PropBank" version="3.1" inuse="+"/>
        <usage resource="PropBank" version="3.4" inuse="+"/>
        <usage resource="AMR" version="2019" inuse="+"/>
        <usage resource="PropBank" version="Flickr 1.0" inuse="+"/>
        </usagenotes>
      <lexlinks>
        <lexlink class="Statement" confidence="0.8" resource="FrameNet" src="manual+strict-conv" version="1.7"/>
        <lexlink class="Reporting" confidence="0.8" resource="FrameNet" src="manual+strict-conv" version="1.7"/>
        <lexlink class="say-37.7-1" confidence="0.8" resource="VerbNet" src="manual+strict-conv" version="verbnet3.3"/>
        <lexlink class="consider-29.9-1" confidence="0.8" resource="VerbNet" src="manual+strict-conv" version="verbnet3.3"/>
        <lexlink class="characterize-29.2-1-2" confidence="0.8" resource="VerbNet" src="manual+strict-conv" version="verbnet3.3"/>
        <lexlink class="characterize-29.2-1-2" confidence="1.0" resource="VerbNet" src="manualchecks" version="verbnet3.4"/>
      </lexlinks>
      <example name="report-v: just the news" src="">
        <text>Commonwealth Edison reported earnings of $ 737 million .</text>
        <propbank>
          <rel relloc="2">reported</rel>
          <arg end="1" start="0" type="ARG0">Commonwealth Edison</arg>
          <arg end="7" start="3" type="ARG1">earnings of $ 737 million</arg>
        </propbank>
      </example>
      <example name="report-v: just hearer" src="">
        <text>He will report to Donald Pardus .</text>
        <propbank>
          <rel relloc="2">report</rel>
          <arg end="0" start="0" type="ARG0">He</arg>
          <arg end="5" start="3" type="ARG2">to Donald Pardus</arg>
        </propbank>
      </example>
      <example name="report-v: passivized" src="">
        <text>Preliminary findings were reported more than a year ago by the AMA</text>
        <propbank>
          <rel relloc="3">reported</rel>
          <arg end="1" start="0" type="ARG1">Preliminary findings</arg>
          <arg end="8" start="4" type="ARGM-TMP">more than a year ago</arg>
          <arg end="11" start="9" type="ARG0">by the AMA</arg>
        </propbank>
      </example>
      <example name="report-v: passive extraction" src="">
        <text>Retail sales were reported slow in most districts .</text>
        <propbank>
          <rel relloc="3">reported</rel>
          <arg end="4" start="4" type="ARG1">slow</arg>
          <arg end="7" start="5" type="ARGM-LOC">in most districts</arg>
        </propbank>
      </example>
      <example name="report-v: another passive extraction" src="">
        <text>Hammersmith is reported to have been sold .</text>
        <propbank>
          <rel relloc="2">reported</rel>
          <arg end="6" start="3" type="ARG1">to have been sold</arg>
        </propbank>
      </example>
      <example name="report-v: untargeted passive" src="">
        <text>This goes past what had been reported before .</text>
        <propbank>
          <rel relloc="6">reported</rel>
          <arg end="3" start="3" type="ARG0">what</arg>
          <arg end="7" start="7" type="ARGM-TMP">before</arg>
        </propbank>
      </example>
      <example name="report-v: fronted" src="">
        <text>The FBI found evidence for an alien invasion , Agt Mulder reported</text>
        <propbank>
          <rel relloc="11">reported</rel>
          <arg end="10" start="9" type="ARG0">Agt Mulder</arg>
          <arg end="7" start="0" type="ARG1">The FBI found evidence for an alien invasion</arg>
        </propbank>
      </example>
      <example name="report-v: inverted" src="">
        <text>Japanese corporations bought South Dakota , reported Newsweek .</text>
        <propbank>
          <rel relloc="6">reported</rel>
          <arg end="4" start="0" type="ARG1">Japanese corporations bought South Dakota</arg>
          <arg end="7" start="7" type="ARG0">Newsweek</arg>
        </propbank>
      </example>
      <example name="report-v: ARG0 and ARG1" src="ontonotes mz/sinorama/10/ectb_1031">
        <text>Also , when Chen Shui - bian visited the Dominican Republic in August , the ROC ambassador there reported that in 1997 , the PRC managed to get the Dominican Republic 's agreement to the establishment of a PRC office in the DR capital by playing on the DR 's desire to extend its consular rights in Hong Kong .</text>
        <propbank>
          <rel relloc="18">reported</rel>
          <arg end="0" start="0" type="ARGM-DIS">Also</arg>
          <arg end="12" start="2" type="ARGM-TMP">when Chen Shui - bian visited the Dominican Republic in August</arg>
          <arg end="17" start="14" type="ARG0">the ROC ambassador there</arg>
          <arg end="58" start="19" type="ARG1">that in 1997 , the PRC managed to get the Dominican Republic 's agreement to the establishment of a PRC office in the DR capital by playing on the DR 's desire to extend its consular rights in Hong Kong</arg>
        </propbank>
      </example>
      <example name="report-n: Example with all args" src="">
        <text>its report to Congress on international economic policies</text>
        <propbank>
          <rel relloc="1">report</rel>
          <arg end="0" start="0" type="ARG0">its</arg>
          <arg end="3" start="2" type="ARG2">to Congress</arg>
          <arg end="7" start="4" type="ARG1">on international economic policies</arg>
        </propbank>
      </example>
      <example name="report-n: Example with only arg 1" src="">
        <text>the trade report</text>
        <propbank>
          <rel relloc="2">report</rel>
          <arg end="1" start="1" type="ARG1">trade</arg>
        </propbank>
      </example>
      <example name="report-n: Example with arg 0 and arg 1" src="">
        <text>Their report on a struggle that affects more than ten million americans</text>
        <propbank>
          <rel relloc="1">report</rel>
          <arg end="0" start="0" type="ARG0">Their</arg>
          <arg end="11" start="2" type="ARG1">on a struggle that affects more than ten million americans</arg>
        </propbank>
      </example>
      <example name="reporting-n: all args" src="internet">
        <text>The inconsistencies in Dorner 's various explanations as to why there was a delay in his reporting the alleged kicks to a supervisor</text>
        <propbank>
          <rel relloc="16">reporting</rel>
          <arg end="15" start="15" type="ARG0">his</arg>
          <arg end="19" start="17" type="ARG1">the alleged kicks</arg>
          <arg end="22" start="20" type="ARG2">to a supervisor</arg>
        </propbank>
      </example>
      <example name="report-n" src="THYME-colon-dir">
        <text>The surgical pathology report describes a grade 3 adenocarcinoma ...</text>
        <propbank>
          <rel relloc="3">report</rel>
          <arg end="2" start="1" type="ARG3">surgical pathology</arg>
        </propbank>
        <amr version="THYME 1.0">
          (d / describe-01
            :ARG0 (r / report-01
              :ARG3 (p / pathology-02
                :ARG1 (t / thing
                  :source (s / surgery-01))))
            :ARG1 (d2 / disease-disorder :name (n / name :op1 "adenocarcinoma")
              :ARG1-of (g / grade-01
                :ARG2 3)))
        </amr>
      </example>
      <note>REPORT NOTES: Arg3 added for THYME-AMR (plus rolelink entries).</note>
      <note>REPORT-V NOTES: Member of Vncls say-37.7-1, consider-29.9-1, characterize-29.2-1-2. Updated by Julia, 10/2010. (from report.01-v)</note>
      <note>REPORT-N NOTES: Roleset based on report.01. Verbnet class say 37.7 and charactorize-29.2. Framed by Katie (from report.01-n)</note>
      <note>REPORTING-N NOTES: Added by Julia based on BOLT-5, report-v.01. Corresponds to VNcls say-37.7-1, consider-29.9-1, characterize-29.2-1-2. (from reporting.01-n)</note>
    </roleset>
    <roleset id="report.02" name="present one's self, show up">
      <aliases>
        <alias pos="v">report</alias>
      </aliases>
      <roles>
        <role descr="person presenting" f="PAG" n="0"/>
        <role descr="to whom, where" f="GOL" n="1"/>
        <role descr="for what (purpose)" f="PRP" n="2"/>
      </roles>
      <usagenotes>
        <usage resource="PropBank" version="1.0" inuse="-"/>
        <usage resource="PropBank" version="2.1.5" inuse="-"/>
        <usage resource="PropBank" version="3.1" inuse="-"/>
        <usage resource="PropBank" version="3.4" inuse="+"/>
        <usage resource="AMR" version="2019" inuse="-"/>
        <usage resource="PropBank" version="Flickr 1.0" inuse="-"/>
        </usagenotes>
      <lexlinks/>
      <example name="report-v" src="THYME-colon-dir">
        <text>Second portion to be completed the day of procedure , 2 hours before your scheduled report time .</text>
        <amr version="THYME 1.0">
          (c / complete-01
            :ARG0 y
            :ARG1 (p / portion)
            :time (d / day
              :time-of (p2 / procedure-01
                :ARG2 y))
            :time (b / before
              :op1 (t / time
                :time-of (r2 / report-02
                  :ARG0 (y / you)
                  :ARG2 p2
                  :ARG1-of (s / schedule-01
                    :ARG3 t)))
              :quant (t2 / temporal-quantity :quant 2
                :unit (h / hour))))
          </amr>
        <propbank>
          <rel relloc="15">report</rel>
          <arg end="16" start="16" type="ARGM-TMP">time</arg>
        </propbank>
      </example>
      <note>REPORT NOTES: Added for THYME-AMR.</note>
    </roleset>
  </predicate>
</frameset>