<?xml version='1.0' encoding='UTF-8'?>
<frameset>
  <predicate lemma="roam">
    <roleset id="roam.01" name="move over a wide area">
      <aliases>
        <alias pos="v">roam</alias>
      </aliases>
      <roles>
        <role descr="entity in motion" f="PPT" n="0">
          <rolelinks>
            <rolelink resource="VerbNet" class="run-51.3.2-1" version="verbnet3.3">theme</rolelink>
            <rolelink resource="FrameNet" class="Self_motion" version="1.7">self_mover</rolelink>
          </rolelinks>
        </role>
        <role descr="range, wide area" f="LOC" n="1">
          <rolelinks>
            <rolelink resource="VerbNet" class="run-51.3.2-1" version="verbnet3.3">location</rolelink>
            <rolelink resource="FrameNet" class="Self_motion" version="1.7">goal</rolelink>
            <rolelink resource="FrameNet" class="Self_motion" version="1.7">path</rolelink>
          </rolelinks>
        </role>
      </roles>
      <usagenotes>
        <usage resource="PropBank" version="3.0" inuse="+"/>
        <usage resource="AMR" version="3.0" inuse="+"/>
      </usagenotes>
      <lexlinks>
        <lexlink resource="FrameNet" class="Self_motion" version="1.7" confidence="0.8" src="manual+strict-conv"/>
        <lexlink resource="VerbNet" class="run-51.3.2-1" version="verbnet3.3" confidence="0.8" src="manual+strict-conv"/>
        <lexlink resource="AidaOntology" version="Jan2019" class="Movement.TransportPerson.SelfMotion" confidence="0.1" src="reo-expansion"/>
        <lexlink resource="ERE" class="Transportperson" version="rich" confidence="0.1" src="reo-expansion"/>
      </lexlinks>
      <example src="" name="jackals?">
        <text>Jackals roam the streets at night, and gemsbok, hardy antelope with long straight horns, wander in from the desert to drink from water sprinklers.</text>
        <rel relloc="1">roam</rel>
        <arg f="" n="0" start="0" end="0">Jackals</arg>
        <arg f="" n="1" start="2" end="3">the streets</arg>
        <arg f="TMP" n="M" start="4" end="5">at night,</arg>
      </example>
      <note>ROAM-V NOTES: Frames file for 'roam' based on sentences in wsj. Verbnet entry 51.3.2, Framenet entry Self motion. (from roam.01-v predicate notes)</note>
    </roleset>
  </predicate>
</frameset>
