<?xml version="1.0" ?>
<frameset>
   <predicate lemma="scab">
      <roleset id="scab.01" name="form a protective crust">
         <aliases>
            <alias pos="n">scabbing</alias>
            <alias pos="v">scab</alias>
         </aliases>
         <roles>
            <role descr="entity with scab" f="PPT" n="1"/>
         </roles>
         <usagenotes>
            <usage inuse="+" resource="PropBank" version="3.0"/>
            <usage inuse="-" resource="AMR" version="3.0"/>
         </usagenotes>
         <lexlinks/>
         <example name="only arg" src="">
            <text>It does not bleed or scab</text>
            <rel relloc="5">scab</rel>
            <arg end="0" f="" n="1" start="0">It</arg>
            <arg end="2" f="NEG" n="m" start="2">not</arg>
         </example>
         <example name="only arg" src="">
            <text>no wound scabbing</text>
            <rel relloc="2">scabbing</rel>
            <arg end="0" f="NEG" n="m" start="0">no</arg>
            <arg end="1" f="" n="1" start="1">wound</arg>
         </example>
         <note>SCAB-V NOTES: Based on Thyme and Stratified data. No comparison. No VN of FN classes. Framed by Katie (from scab.01-v)</note>
         <note>SCABBING-N NOTES: Based on Thyme and Sharp data. Comparison to scab.01. No VN or FN classes. Framed by Katie. (from scabbing.01-n)</note>
      </roleset>
   </predicate>
</frameset>
