<?xml version="1.0" encoding="utf-8" standalone="no"?>
<!DOCTYPE frameset PUBLIC "-//PB//PropBank Frame v3.4 Transitional//EN" "http://propbank.org/specification/dtds/v3.4/frameset.dtd">
<frameset>
  <predicate lemma="shortcoming">
    <roleset id="shortcoming.01" name="coming up short">
      <aliases>
        <alias pos="n">shortcoming</alias>
      </aliases>
      <roles>
        <role descr="entity coming up short" f="PAG" n="0"/>
        <role descr="domain in which arg1 is coming up short" f="VSP" n="1"/>
      </roles>
      <usagenotes>
        <usage resource="PropBank" version="1.0" inuse="-"/>
        <usage resource="PropBank" version="2.1.5" inuse="-"/>
        <usage resource="PropBank" version="3.1" inuse="+"/>
        <usage resource="PropBank" version="3.4" inuse="+"/>
        <usage resource="AMR" version="2019" inuse="-"/>
        <usage resource="PropBank" version="Flickr 1.0" inuse="+"/>
        </usagenotes>
      <lexlinks/>
      <example name="arg0" src="BOLT">
        <text>He was n't the head of the ECB but one of the Vice Presidents , ie in the governing council of the ECB . For all the shortcomings of the Euro , I ca n't see how the ECB has done a bad job .</text>
        <propbank>
          <rel relloc="27">shortcomings</rel>
          <arg type="ARG0" start="28" end="30">of the Euro</arg>
        </propbank>
      </example>
      <example name="Both args" src="internet">
        <text>McCain tapped his good friend Phil Gramm to help with his economic shortcomings .</text>
        <propbank>
          <rel relloc="12">shortcomings</rel>
          <arg type="ARG0" start="10" end="10">his</arg>
          <arg type="ARG1" start="11" end="11">economic</arg>
        </propbank>
      </example>
      <note>SHORTCOMING-N NOTES: Added by Julia based on BOLT. No VNcls. (from shortcoming.01-n)</note>
    </roleset>
  </predicate>
</frameset>