<!DOCTYPE frameset SYSTEM "frameset.dtd">
<frameset>
<note/>
<predicate lemma="superstition">
<note/>
<roleset framnet="-" id="superstition.01" name="strict belief in logically unrelated causes and effects" source="-" vncls="-">
<roles>
<role descr="believer" f="pag" n="0"/>
<note/>
<role descr="belief" f="ppt" n="1"/>
</roles>
<note>Added by Julia based on BOLT-7.</note>
<example name="ADJ" src="BOLT-7" type="">
<inflection aspect="ns" form="ns" person="ns" tense="ns" voice="ns"/>
<text>Now , the domestic feudal superstition floods in , some places build temples in the name of tourism , and , to a certain extent , these temples that are built affect people 's ideological choice ; many people begin to have dual beliefs .</text>
<note>Here, it is unclear exactly what the superstition is, but it has to do with the issue of domestic feudalism.</note>
<arg f="adj" n="m">[domestic] [feudal]</arg>
<rel f="">superstition</rel>
</example>
</roleset>
</predicate>
</frameset>
