<?xml version='1.0' encoding='UTF-8'?>
<frameset>
  <predicate lemma="teach">
    <roleset id="teach.01" name="(try to) make learn, causing to learn">
      <aliases>
        <alias pos="n">teaching</alias>
        <alias pos="v">teach</alias>
        <argalias pos="n" arg="0">teacher</argalias>
      </aliases>
      <roles>
        <role descr="teacher" f="PAG" n="0">
          <rolelinks>
            <rolelink resource="VerbNet" class="transfer_mesg-37.1.1-1-1" version="verbnet3.3">agent</rolelink>
          </rolelinks>
        </role>
        <role descr="subject" f="PPT" n="1">
          <rolelinks>
            <rolelink resource="VerbNet" class="transfer_mesg-37.1.1-1-1" version="verbnet3.3">topic</rolelink>
          </rolelinks>
        </role>
        <role descr="student(s)" f="GOL" n="2">
          <rolelinks>
            <rolelink resource="VerbNet" class="transfer_mesg-37.1.1-1-1" version="verbnet3.3">recipient</rolelink>
          </rolelinks>
        </role>
      </roles>
      <usagenotes>
        <usage resource="PropBank" version="3.0" inuse="+"/>
        <usage resource="AMR" version="2019" inuse="+"/>
      </usagenotes>
      <lexlinks>
        <lexlink resource="FrameNet" class="Education_teaching" version="1.7" confidence="0.5" src="manual"/>
        <lexlink resource="VerbNet" class="transfer_mesg-37.1.1-1-1" version="verbnet3.3" confidence="0.5" src="manual"/>
        <lexlink resource="onsense" version="on5" class="teach-v.1" src="annot-overlap" confidence="0.1">91</lexlink>
      </lexlinks>
      <example src="" name="intransitive">
        <text>She was an unstinting teacher who won laurels and inspired students, but she will probably never teach again.</text>
        <rel relloc="16">teach</rel>
        <arg f="" n="0" start="0" end="0">She</arg>
        <arg f="MOD" n="m" start="13" end="13">will</arg>
        <arg f="ADV" n="m" start="14" end="14">probably</arg>
        <arg f="NEG" n="m" start="15" end="15">never</arg>
        <arg f="TMP" n="m" start="17" end="17">again.</arg>
      </example>
      <example src="" name="just subject">
        <text>The group says standardized achievement test scores are greatly inflated because teachers often ``teach the test'' as Mrs. Yeargin did, although most are never caught.</text>
        <rel relloc="13">``teach</rel>
        <arg f="" n="0" start="11" end="11">teachers</arg>
        <arg f="TMP" n="m" start="12" end="12">often</arg>
        <arg f="" n="1" start="14" end="15">the test''</arg>
        <arg f="MNR" n="m" start="16" end="19">as Mrs. Yeargin did,</arg>
      </example>
      <example src="" name="just students">
        <text>Encouraged by Mrs. Ward, Mrs. Yeargin taught honor students in the state ``teacher cadet'' program, a reform creation designed to encourage good students to consider teaching as a career.</text>
        <rel relloc="6">taught</rel>
        <arg f="" n="0" start="4" end="5">Mrs. Yeargin</arg>
        <arg f="" n="2" start="7" end="28">honor students in the state ``teacher cadet'' program, a reform creation designed to encourage good students to consider teaching as a career.</arg>
      </example>
      <example src="" name="double object">
        <text>``She taught us more in Western Civilization than I've ever learned in other classes,'' says Kelli Green, a Greenville senior.</text>
        <rel relloc="1">taught</rel>
        <arg f="" n="0" start="0" end="0">``She</arg>
        <arg f="" n="2" start="2" end="2">us</arg>
        <arg f="" n="1" start="3" end="13">more in Western Civilization than I've ever learned in other classes,''</arg>
      </example>
      <example src="ontonotes mz/sinorama/10/ectb_1075" name="ARG0 and ARG1 and ARG2">
        <text>Singing songs is a popular technique for teaching English to kids .</text>
        <rel relloc="7">teaching</rel>
        <arg f="" n="1" start="8" end="8">English</arg>
        <arg f="" n="2" start="9" end="10">to kids</arg>
      </example>
      <note>TEACH-V NOTES: Member of VNcls transfer_mesg-37.1.1-1-1. (from teach.01-v)</note>
      <note>TEACHING-N NOTES: teach.01 (from teaching.01-n)</note>
    </roleset>
  </predicate>
</frameset>
